captcha/__init__.py
captcha/detect.py
captcha_utils-0.0.2.dist-info/METADATA
captcha_utils-0.0.2.dist-info/WHEEL
captcha_utils-0.0.2.dist-info/top_level.txt
captcha_utils-0.0.2.dist-info/RECORD
