Metadata-Version: 2.1
Name: captcha-utils
Version: 0.0.2
Summary: A package to solve captcha
Home-page: https://github.com/Juannie-PP/captcha-utils
Author: Juannie-PP
Author-email: 2604868278@qq.com
License: MIT
Platform: UNKNOWN
Classifier: Programming Language :: Python :: 3
Requires-Python: >=3.6
Requires-Dist: requests (>=2.19.1)
Requires-Dist: numpy (>=1.23.0)
Requires-Dist: opencv-python (==4.5.5.64)
